insta_cs/__init__.py
insta_cs/client.py
insta_cs/compat.py
insta_cs/compatpatch.py
insta_cs/constants.py
insta_cs/errors.py
insta_cs/http.py
insta_cs/utils.py
insta_cs/endpoints/__init__.py
insta_cs/endpoints/accounts.py
insta_cs/endpoints/collections.py
insta_cs/endpoints/common.py
insta_cs/endpoints/discover.py
insta_cs/endpoints/feed.py
insta_cs/endpoints/friendships.py
insta_cs/endpoints/highlights.py
insta_cs/endpoints/igtv.py
insta_cs/endpoints/live.py
insta_cs/endpoints/locations.py
insta_cs/endpoints/media.py
insta_cs/endpoints/misc.py
insta_cs/endpoints/tags.py
insta_cs/endpoints/upload.py
insta_cs/endpoints/users.py
insta_cs/endpoints/usertags.py
insta_web_cs/__init__.py
insta_web_cs/client.py
insta_web_cs/common.py
insta_web_cs/compat.py
insta_web_cs/compatpatch.py
insta_web_cs/errors.py
insta_web_cs/http.py
insta_cs-1.0.4.dist-info/LICENSE
insta_cs-1.0.4.dist-info/METADATA
insta_cs-1.0.4.dist-info/WHEEL
insta_cs-1.0.4.dist-info/top_level.txt
insta_cs-1.0.4.dist-info/RECORD
