Metadata-Version: 2.1
Name: insta-cs
Version: 1.0.4
Summary: A client interface for the Instagram automation.
Author: Charan
Author-email: firstmodified@gmail.com
License: MIT
Keywords: insta_cs instagram
Platform: any
Classifier: Development Status :: 4 - Beta
Classifier: Intended Audience :: Developers
Classifier: License :: OSI Approved :: MIT License
Classifier: Topic :: Software Development :: Libraries :: Python Modules
Classifier: Programming Language :: Python :: 2.7
Classifier: Programming Language :: Python :: 3.5
Classifier: Programming Language :: Python :: 3.6
License-File: LICENSE
